[
  {
    "id": 1758577020817,
    "name": "Mark 2.0.xlsx",
    "email": "sales@devello.us",
    "subject": "wd",
    "message": "wd",
    "created_at": "2025-09-22T21:37:00.817Z",
    "status": "new"
  },
  {
    "id": 1760236358468,
    "name": "dwa",
    "email": "sales@devello.us",
    "subject": "dwa",
    "message": "wadda",
    "created_at": "2025-10-12T02:32:38.468Z",
    "status": "new"
  },
  {
    "id": 1760236411276,
    "name": "wda",
    "email": "sales@devello.us",
    "subject": "awd",
    "message": "wad",
    "created_at": "2025-10-12T02:33:31.276Z",
    "status": "new"
  }
]